LICENSE
MANIFEST.in
README
README.ja
setup.cfg
setup.py
tuitwirc.yml
tuitwi/__init__.py
tuitwi/const.py
tuitwi/state.py
tuitwi/ui.py
tuitwi/updater.py
tuitwi/widechartools.py
tuitwi.egg-info/PKG-INFO
tuitwi.egg-info/SOURCES.txt
tuitwi.egg-info/dependency_links.txt
tuitwi.egg-info/entry_points.txt
tuitwi.egg-info/requires.txt
tuitwi.egg-info/top_level.txt
tuitwi.egg-info/zip-safe