Metadata-Version: 1.0
Name: tuitwi
Version: 0.4dev
Summary: TUI twitter client
Home-page: http://github.com/seikichi/tuitwi
Author: seikichi
Author-email: seikichi@kmc.gr.jp
License: MIT
Keywords: curses tui twitter
Platform: UNKNOWN
Classifier: Development Status :: 4 - Beta
Classifier: Environment :: Console :: Curses
Classifier: Natural Language :: Japanese
Classifier: Intended Audience :: End Users/Desktop
Classifier: License :: OSI Approved :: MIT License
Classifier: Programming Language :: Python
Classifier: Topic :: Communications
